word2word/__init__.py
word2word/methods.py
word2word/supporting_languages.txt
word2word/tokenization.py
word2word/utils.py
word2word/word2word.py
word2word-1.0.0.dist-info/LICENSE
word2word-1.0.0.dist-info/METADATA
word2word-1.0.0.dist-info/WHEEL
word2word-1.0.0.dist-info/top_level.txt
word2word-1.0.0.dist-info/RECORD
