Metadata-Version: 2.1
Name: word2word
Version: 1.0.0
Summary: Easy-to-use word translations for 3,564 language pairs
Home-page: https://github.com/kakaobrain/word2word
Author: Kyubyong Park, Dongwoo Kim, Yo Joong Choe
Author-email: kbpark.linguist@gmail.com, kimdwkimdw@gmail.com, yjchoe33@gmail.com
License: Apache License 2.0
Platform: UNKNOWN
Classifier: Development Status :: 5 - Production/Stable
Classifier: Intended Audience :: Developers
Classifier: Intended Audience :: Science/Research
Classifier: License :: OSI Approved :: Apache Software License
Classifier: Operating System :: OS Independent
Classifier: Programming Language :: Python :: 3
Classifier: Programming Language :: Python :: 3.6
Classifier: Programming Language :: Python :: 3.7
Requires-Python: >=3.6
